[
    {
        "name": "Trishaa Raj",
        "passkey": "trisha",
        "age": 21,
        "place": "india",
        "friends": [],
        "todo": [],
        "status": "",
        "spousename": ""
    },
    {
        "name": "Antony",
        "passkey": "wiplash",
        "age": 20,
        "place": "india",
        "friends": [],
        "todo": [],
        "status": "",
        "spousename": ""
    },
    {
        "name": "joshua",
        "passkey": "joshua",
        "age": 10,
        "place": "coorg",
        "friends": [],
        "todo": [],
        "status": "",
        "spousename": ""
    }
]